acr122u_websocket/__init__.py
acr122u_websocket/app.py
acr122u_websocket/my_reader.py
acr122u_websocket/reader_helpers.py
acr122u_websocket/templates/test.html
acr122u_websocket-1.1.4.dist-info/LICENSE
acr122u_websocket-1.1.4.dist-info/METADATA
acr122u_websocket-1.1.4.dist-info/WHEEL
acr122u_websocket-1.1.4.dist-info/top_level.txt
acr122u_websocket-1.1.4.dist-info/RECORD
