Metadata-Version: 2.1
Name: acr122u-websocket
Version: 1.1.4
Summary: A webserver that connects to a acr122u and exposes it over websocket
Author-email: Robert van Dijk <contact@robertvandijk.nl>
Project-URL: Homepage, https://github.com/robertdijk/acr122u-websocket
Keywords: nfc,acr,acr122u,websocket,web
Classifier: License :: OSI Approved :: GNU General Public License v3 (GPLv3)
Classifier: Programming Language :: Python
Classifier: Programming Language :: Python :: 3
Requires-Python: >=3.11
License-File: LICENSE
Requires-Dist: flask
Requires-Dist: flask-socketio
Requires-Dist: py-acr122u
Provides-Extra: dev
Requires-Dist: bumpver ; extra == 'dev'
Requires-Dist: black ; extra == 'dev'
